openpdk_pmap/__init__.py
openpdk_pmap/__main__.py
openpdk_pmap/pmap.py
openpdk_pmap/version.py
openpdk_pmap-0.0.1.dist-info/LICENSE
openpdk_pmap-0.0.1.dist-info/METADATA
openpdk_pmap-0.0.1.dist-info/WHEEL
openpdk_pmap-0.0.1.dist-info/entry_points.txt
openpdk_pmap-0.0.1.dist-info/RECORD
