Metadata-Version: 2.3
Name: openpdk-pmap
Version: 0.0.1
Summary: pmap replacement for OpenPDK LVS scripts
License: GPL-3.0-or-later
Keywords: electronic,pex,parasitic,extraction,vlsi,eda,ic,spice,klayout,analog,fsic,gds,FasterCap,magic
Author: Martin Köhler
Author-email: info@martinjankoehler.com
Requires-Python: >=3.12,<4.0
Classifier: Development Status :: 2 - Pre-Alpha
Classifier: Environment :: Console
Classifier: Intended Audience :: Manufacturing
Classifier: Intended Audience :: Science/Research
Classifier: License :: OSI Approved :: GNU General Public License v3 or later (GPLv3+)
Classifier: Operating System :: MacOS
Classifier: Operating System :: Microsoft :: Windows
Classifier: Operating System :: POSIX
Classifier: Programming Language :: C++
Classifier: Programming Language :: Python :: 3
Classifier: Programming Language :: Python :: 3.12
Classifier: Programming Language :: Python :: 3.13
Classifier: Programming Language :: Python :: 3 :: Only
Classifier: Topic :: Scientific/Engineering
Classifier: Topic :: Scientific/Engineering :: Electronic Design Automation (EDA)
Requires-Dist: psutil (>=7.0.0,<8.0.0)
Project-URL: Bug Tracker, https://github.com/martinjankoehler/openpdk-pmap/issues
Project-URL: Homepage, https://martinjankoehler.github.io/openpdk-pmap/
Project-URL: Repository, https://github.com/martinjankoehler/openpdk-pmap.git
